Assignment 2/ALU.vhdl
library IEEE;
use IEEE.STD_LOGIC_1164.ALL;
use IEEE.NUMERIC_STD.ALL;
 
entity alu is
 Port ( inp_a : in signed(3 downto 0);
 inp_b : in signed(3 downto 0);
 sel : in STD_LOGIC_VECTOR (2 downto 0);
 out_alu : out signed(3 downto 0));
end alu;
 
architecture Behavioral of alu is
begin
process(inp_a, inp_b, sel)
begin
case sel is
 when "000" =>
 out_alu<= inp_a + inp_b;
 when "001" =>
 out_alu<= inp_a - inp_b;
 out_alu<= inp_a - 1;
 when "011" =>
 out_alu<= inp_a + 1;
 when "100" =>
 out_alu<= inp_a and inp_b;
 when "101" =>
 out_alu<= inp_a or inp_b;
 when "110" =>
 out_alu<= not inp_a ;
 when "111" =>
 out_alu<= inp_a xor inp_b;
 when others =>
 NULL;
end case;
  
end process;
 
end Behavioral;

Assignment2/ALU_tb.vhdl
LIBRARY ieee;
USE ieee.std_logic_1164.ALL;
USE ieee.numeric_std.ALL;
  
ENTITY ALU_tb IS
END ALU_tb;
  
ARCHITECTURE behavior OF ALU_tb IS
  

  
 COMPONENT alu
 PORT(
 inp_a : IN signed(3 downto 0);
 inp_b : IN signed(3 downto 0);
 sel : IN std_logic_vector(2 downto 0);
 out_alu : OUT signed(3 downto 0)
 );
 END COMPONENT;
  
 

 signal inp_a : signed(3 downto 0) := (others => '0');
 signal inp_b : signed(3 downto 0) := (others => '0');
 signal sel : std_logic_vector(2 downto 0) := (others => '0');
 

 signal out_alu : signed(3 downto 0);
  
BEGIN
  

 uut: alu PORT MAP (
 inp_a => inp_a,
 inp_b => inp_b,
 sel => sel,
 out_alu => out_alu
 );
 

 stim_proc: process
 begin

 wait for 100 ns;
 

 
 inp_a <= "1001";
 inp_b <= "1111";
  
 sel <= "000";
 wait for 100 ns;
 sel <= "001";
 wait for 100 ns;
 sel <= "010";
 wait for 100 ns;
 sel <= "011";
 wait for 100 ns;
 sel <= "100";
 wait for 100 ns;
 sel <= "101";
 wait for 100 ns;
 sel <= "110";
 wait for 100 ns;
 sel <= "111";
 
 assert false report "Reached end of test bench";
 end process;
 
END;

Assignment 2/ALU.vcd
$date
  Sat Feb 12 21:51:38 2022
$end
$version
  GHDL v0
$end
$timescale
  1 fs
$end
$scope module standard $end
$upscope $end
$scope module std_logic_1164 $end
$upscope $end
$scope module numeric_std $end
$upscope $end
$scope module alu_tb $end
$var reg 4 ! inp_a[3:0] $end
$var reg 4 " inp_b[3:0] $end
$var reg 3 # sel[2:0] $end
$var reg 4 $ out_alu[3:0] $end
$scope module uut $end
$var reg 4 % inp_a[3:0] $end
$var reg 4 & inp_b[3:0] $end
$var reg 3 ' sel[2:0] $end
$var reg 4 ( out_alu[3:0] $end
$upscope $end
$upscope $end
$enddefinitions $end
#0
b0000 !
b0000 "
b000 #
b0000 $
b0000 %
b0000 &
b000 '
b0000 (
#100000000
b1001 !
b1111 "
b1000 $
b1001 %
b1111 &
b1000 (
#200000000
b001 #
b001 '
b1000 (
#300000000
b010 #
b010 '
#400000000
b011 #
b1010 $
b011 '
b1010 (
#500000000
b100 #
b1001 $
b100 '
b1001 (
#600000000
b101 #
b1111 $
b101 '
b1111 (
#700000000
b110 #
b0110 $
b110 '
b0110 (
#800000000
b111 #
b111 '
#900000000
b000 #
b1000 $
b000 '
b1000 (
#1000000000
b001 #
b001 '
b1000 (
#1100000000
b010 #
b010 '
#1200000000
b011 #
b1010 $
b011 '
b1010 (
#1300000000
b100 #
b1001 $
b100 '
b1001 (
#1400000000
b101 #
b1111 $
b101 '
b1111 (
#1500000000
b110 #
b0110 $
b110 '
b0110 (
#1600000000
b111 #
b111 '
#1700000000
b000 #
b1000 $
b000 '
b1000 (
#1800000000
b001 #
b001 '
b1000 (
#1900000000
b010 #
b010 '
#2000000000
b011 #
b1010 $
b011 '
b1010 (
#2100000000
b100 #
b1001 $
b100 '
b1001 (
#2200000000
b101 #
b1111 $
b101 '
b1111 (
#2300000000
b110 #
b0110 $
b110 '
b0110 (
#2400000000
b111 #
b111 '
#2500000000
b000 #
b1000 $
b000 '
b1000 (
#2600000000
b001 #
b001 '
b1000 (
#2700000000
b010 #
b010 '
#2800000000
b011 #
b1010 $
b011 '
b1010 (
#2900000000
b100 #
b1001 $
b100 '
b1001 (
#3000000000
b101 #
b1111 $
b101 '
b1111 (
#3100000000
b110 #
b0110 $
b110 '
b0110 (
#3200000000
b111 #
b111 '
#3300000000
b000 #
b1000 $
b000 '
b1000 (
#3400000000
b001 #
b001 '
b1000 (
#3500000000
b010 #
b010 '
#3600000000
b011 #
b1010 $
b011 '
b1010 (
#3700000000
b100 #
b1001 $
b100 '
b1001 (
#3800000000
b101 #
b1111 $
b101 '
b1111 (
#3900000000
b110 #
b0110 $
b110 '
b0110 (
#4000000000
b111 #
b111 '
#4100000000
b000 #
b1000 $
b000 '
b1000 (
#4200000000
b001 #
b001 '
b1000 (
#4300000000
b010 #
b010 '
#4400000000
b011 #
b1010 $
b011 '
b1010 (
#4500000000
b100 #
b1001 $
b100 '
b1001 (
#4600000000
b101 #
b1111 $
b101 '
b1111 (
#4700000000
b110 #
b0110 $
b110 '
b0110 (
#4800000000
b111 #
b111 '
#4900000000
b000 #
b1000 $
b000 '
b1000 (
#5000000000
b001 #
b001 '
b1000 (
#5100000000
b010 #
b010 '
#5200000000
b011 #
b1010 $
b011 '
b1010 (
#5300000000
b100 #
b1001 $
b100 '
b1001 (
#5400000000
b101 #
b1111 $
b101 '
b1111 (
#5500000000
b110 #
b0110 $
b110 '
b0110 (
#5600000000
b111 #
b111 '
#5700000000
b000 #
b1000 $
b000 '
b1000 (
#5800000000
b001 #
b001 '
b1000 (
#5900000000
b010 #
b010 '
#6000000000
b011 #
b1010 $
b011 '
b1010 (
#6100000000
b100 #
b1001 $
b100 '
b1001 (
#6200000000
b101 #
b1111 $
b101 '
b1111 (
#6300000000
b110 #
b0110 $
b110 '
b0110 (
#6400000000
b111 #
b111 '
#6500000000
b000 #
b1000 $
b000 '
b1000 (
#6600000000
b001 #
b001 '
b1000 (
#6700000000
b010 #
b010 '
#6800000000
b011 #
b1010 $
b011 '
b1010 (
#6900000000
b100 #
b1001 $
b100 '
b1001 (
#7000000000
b101 #
b1111 $
b101 '
b1111 (
#7100000000
b110 #
b0110 $
b110 '
b0110 (
#7200000000
b111 #
b111 '
#7300000000
b000 #
b1000 $
b000 '
b1000 (
#7400000000
b001 #
b001 '
b1000 (
#7500000000
b010 #
b010 '
#7600000000
b011 #
b1010 $
b011 '
b1010 (
#7700000000
b100 #
b1001 $
b100 '
b1001 (
#7800000000
b101 #
b1111 $
b101 '
b1111 (
#7900000000
b110 #
b0110 $
b110 '
b0110 (
#8000000000
b111 #
b111 '
#8100000000
b000 #
b1000 $
b000 '
b1000 (
#8200000000
b001 #
b001 '
b1000 (
#8300000000
b010 #
b010 '
#8400000000
b011 #
b1010 $
b011 '
b1010 (
#8500000000
b100 #
b1001 $
b100 '
b1001 (
#8600000000
b101 #
b1111 $
b101 '
b1111 (
#8700000000
b110 #
b0110 $
b110 '
b0110 (
#8800000000
b111 #
b111 '
#8900000000
b000 #
b1000 $
b000 '
b1000 (
#9000000000
b001 #
b001 '
b1000 (
#9100000000
b010 #
b010 '
#9200000000
b011 #
b1010 $
b011 '
b1010 (
#9300000000
b100 #
b1001 $
b100 '
b1001 (
#9400000000
b101 #
b1111 $
b101 '
b1111 (
#9500000000
b110 #
b0110 $
b110 '
b0110 (
#9600000000
b111 #
b111 '
#9700000000
b000 #
b1000 $
b000 '
b1000 (
#9800000000
b001 #
b001 '
b1000 (
#9900000000
b010 #
b010 '
#10000000000
b011 #
b1010 $
b011 '
b1010 (
#10100000000
b100 #
b1001 $
b100 '
b1001 (
#10200000000
b101 #
b1111 $
b101 '
b1111 (
#10300000000
b110 #
b0110 $
b110 '
b0110 (
#10400000000
b111 #
b111 '
#10500000000
b000 #
b1000 $
b000 '
b1000 (
#10600000000
b001 #
b001 '
b1000 (
#10700000000
b010 #
b010 '
#10800000000
b011 #
b1010 $
b011 '
b1010 (
#10900000000
b100 #
b1001 $
b100 '
b1001 (
#11000000000
b101 #
b1111 $
b101 '
b1111 (
#11100000000
b110 #
b0110 $
b110 '
b0110 (
#11200000000
b111 #
b111 '
#11300000000
b000 #
b1000 $
b000 '
b1000 (
#11400000000
b001 #
b001 '
b1000 (
#11500000000
b010 #
b010 '
#11600000000
b011 #
b1010 $
b011 '
b1010 (
#11700000000
b100 #
b1001 $
b100 '
b1001 (
#11800000000
b101 #
b1111 $
b101 '
b1111 (
#11900000000
b110 #
b0110 $
b110 '
b0110 (
#12000000000
b111 #
b111 '
#12100000000
b000 #
b1000 $
b000 '
b1000 (
#12200000000
b001 #
b001 '
b1000 (
#12300000000
b010 #
b010 '
#12400000000
b011 #
b1010 $
b011 '
b1010 (
#12500000000
b100 #
b1001 $
b100 '
b1001 (
#12600000000
b101 #
b1111 $
b101 '
b1111 (
#12700000000
b110 #
b0110 $
b110 '
b0110 (
#12800000000
b111 #
b111 '
#12900000000
b000 #
b1000 $
b000 '
b1000 (
#13000000000
b001 #
b001 '
b1000 (
#13100000000
b010 #
b010 '
#13200000000
b011 #
b1010 $
b011 '
b1010 (
#13300000000
b100 #
b1001 $
b100 '
b1001 (
#13400000000
b101 #
b1111 $
b101 '
b1111 (
#13500000000
b110 #
b0110 $
b110 '
b0110 (
#13600000000
b111 #
b111 '
#13700000000
b000 #
b1000 $
b000 '
b1000 (
#13800000000
b001 #
b001 '
b1000 (
#13900000000
b010 #
b010 '
#14000000000
b011 #
b1010 $
b011 '
b1010 (
#14100000000
b100 #
b1001 $
b100 '
b1001 (
#14200000000
b101 #
b1111 $
b101 '
b1111 (
#14300000000
b110 #
b0110 $
b110 '
b0110 (
#14400000000
b111 #
b111 '
#14500000000
b000 #
b1000 $
b000 '
b1000 (
#14600000000
b001 #
b001 '
b1000 (
#14700000000
b010 #
b010 '
#14800000000
b011 #
b1010 $
b011 '
b1010 (
#14900000000
b100 #
b1001 $
b100 '
b1001 (
#15000000000
b101 #
b1111 $
b101 '
b1111 (
#15100000000
b110 #
b0110 $
b110 '
b0110 (
#15200000000
b111 #
b111 '
#15300000000
b000 #
b1000 $
b000 '
b1000 (
#15400000000
b001 #
b001 '
b1000 (
#15500000000
b010 #
b010 '
#15600000000
b011 #
b1010 $
b011 '
b1010 (
#15700000000
b100 #
b1001 $
b100 '
b1001 (
#15800000000
b101 #
b1111 $
b101 '
b1111 (
#15900000000
b110 #
b0110 $
b110 '
b0110 (
#16000000000
b111 #
b111 '
#16100000000
b000 #
b1000 $
b000 '
b1000 (
#16200000000
b001 #
b001 '
b1000 (
#16300000000
b010 #
b010 '
#16400000000
b011 #
b1010 $
b011 '
b1010 (
#16500000000
b100 #
b1001 $
b100 '
b1001 (
#16600000000
b101 #
b1111 $
b101 '
b1111 (
#16700000000
b110 #
b0110 $
b110 '
b0110 (
#16800000000
b111 #
b111 '
#16900000000
b000 #
b1000 $
b000 '
b1000 (
#17000000000
b001 #
b001 '
b1000 (
#17100000000
b010 #
b010 '
#17200000000
b011 #
b1010 $
b011 '
b1010 (
#17300000000
b100 #
b1001 $
b100 '
b1001 (
#17400000000
b101 #
b1111 $
b101 '
b1111 (
#17500000000
b110 #
b0110 $
b110 '
b0110 (
#17600000000
b111 #
b111 '
#17700000000
b000 #
b1000 $
b000 '
b1000 (
#17800000000
b001 #
b001 '
b1000 (
#17900000000
b010 #
b010 '
#18000000000
b011 #
b1010 $
b011 '
b1010 (
#18100000000
b100 #
b1001 $
b100 '
b1001 (
#18200000000
b101 #
b1111 $
b101 '
b1111 (
#18300000000
b110 #
b0110 $
b110 '
b0110 (
#18400000000
b111 #
b111 '
#18500000000
b000 #
b1000 $
b000 '
b1000 (
#18600000000
b001 #
b001 '
b1000 (
#18700000000
b010 #
b010 '
#18800000000
b011 #
b1010 $
b011 '
b1010 (
#18900000000
b100 #
b1001 $
b100 '
b1001 (
#19000000000
b101 #
b1111 $
b101 '
b1111 (
#19100000000
b110 #
b0110 $
b110 '
b0110 (
#19200000000
b111 #
b111 '
#19300000000
b000 #
b1000 $
b000 '
b1000 (
#19400000000
b001 #
b001 '
b1000 (
#19500000000
b010 #
b010 '
#19600000000
b011 #
b1010 $
b011 '
b1010 (
#19700000000
b100 #
b1001 $
b100 '
b1001 (
#19800000000
b101 #
b1111 $
b101 '
b1111 (
#19900000000
b110 #
b0110 $
b110 '
b0110 (
#20000000000
b111 #
b111 '
#20100000000
b000 #
b1000 $
b000 '
b1000 (
#20200000000
b001 #
b001 '
b1000 (
#20300000000
b010 #
b010 '
#20400000000
b011 #
b1010 $
b011 '
b1010 (
#20500000000
b100 #
b1001 $
b100 '
b1001 (
#20600000000
b101 #
b1111 $
b101 '
b1111 (
#20700000000
b110 #
b0110 $
b110 '
b0110 (
#20800000000
b111 #
b111 '
#20900000000
b000 #
b1000 $
b000 '
b1000 (
#21000000000
b001 #
b001 '
b1000 (
#21100000000
b010 #
b010 '
#21200000000
b011 #
b1010 $
b011 '
b1010 (
#21300000000
b100 #
b1001 $
b100 '
b1001 (
#21400000000
b101 #
b1111 $
b101 '
b1111 (
#21500000000
b110 #
b0110 $
b110 '
b0110 (
#21600000000
b111 #
b111 '
#21700000000
b000 #
b1000 $
b000 '
b1000 (
#21800000000
b001 #
b001 '
b1000 (
#21900000000
b010 #
b010 '
#22000000000
b011 #
b1010 $
b011 '
b1010 (
#22100000000
b100 #
b1001 $
b100 '
b1001 (
#22200000000
b101 #
b1111 $
b101 '
b1111 (
#22300000000
b110 #
b0110 $
b110 '
b0110 (
#22400000000
b111 #
b111 '
#22500000000
b000 #
b1000 $
b000 '
b1000 (
#22600000000
b001 #
b001 '
b1000 (
#22700000000
b010 #
b010 '
#22800000000
b011 #
b1010 $
b011 '
b1010 (
#22900000000
b100 #
b1001 $
b100 '
b1001 (
#23000000000
b101 #
b1111 $
b101 '
b1111 (
#23100000000
b110 #
b0110 $
b110 '
b0110 (
#23200000000
b111 #
b111 '
#23300000000
b000 #
b1000 $
b000 '
b1000 (
#23400000000
b001 #
b001 '
b1000 (
#23500000000
b010 #
b010 '
#23600000000
b011 #
b1010 $
b011 '
b1010 (
#23700000000
b100 #
b1001 $
b100 '
b1001 (
#23800000000
b101 #
b1111 $
b101 '
b1111 (
#23900000000
b110 #
b0110 $
b110 '
b0110 (
#24000000000
b111 #
b111 '
#24100000000
b000 #
b1000 $
b000 '
b1000 (
#24200000000
b001 #
b001 '
b1000 (
#24300000000
b010 #
b010 '
#24400000000
b011 #
b1010 $
b011 '
b1010 (
#24500000000
b100 #
b1001 $
b100 '
b1001 (
#24600000000
b101 #
b1111 $
b101 '
b1111 (
#24700000000
b110 #
b0110 $
b110 '
b0110 (
#24800000000
b111 #
b111 '
#24900000000
b000 #
b1000 $
b000 '
b1000 (
#25000000000
b001 #
b001 '
b1000 (
#25100000000
b010 #
b010 '
#25200000000
b011 #
b1010 $
b011 '
b1010 (
#25300000000
b100 #
b1001 $
b100 '
b1001 (
#25400000000
b101 #
b1111 $
b101 '
b1111 (
#25500000000
b110 #
b0110 $
b110 '
b0110 (
#25600000000
b111 #
b111 '
#25700000000
b000 #
b1000 $
b000 '
b1000 (
#25800000000
b001 #
b001 '
b1000 (
#25900000000
b010 #
b010 '
#26000000000
b011 #
b1010 $
b011 '
b1010 (
#26100000000
b100 #
b1001 $
b100 '
b1001 (
#26200000000
b101 #
b1111 $
b101 '
b1111 (
#26300000000
b110 #
b0110 $
b110 '
b0110 (
#26400000000
b111 #
b111 '
#26500000000
b000 #
b1000 $
b000 '
b1000 (
#26600000000
b001 #
b001 '
b1000 (
#26700000000
b010 #
b010 '
#26800000000
b011 #
b1010 $
b011 '
b1010 (
#26900000000
b100 #
b1001 $
b100 '
b1001 (
#27000000000
b101 #
b1111 $
b101 '
b1111 (
#27100000000
b110 #
b0110 $
b110 '
b0110 (
#27200000000
b111 #
b111 '
#27300000000
b000 #
b1000 $
b000 '
b1000 (
#27400000000
b001 #
b001 '
b1000 (
#27500000000
b010 #
b010 '
#27600000000
b011 #
b1010 $
b011 '
b1010 (
#27700000000
b100 #
b1001 $
b100 '
b1001 (
#27800000000
b101 #
b1111 $
b101 '
b1111 (
#27900000000
b110 #
b0110 $
b110 '
b0110 (
#28000000000
b111 #
b111 '
#28100000000
b000 #
b1000 $
b000 '
b1000 (
#28200000000
b001 #
b001 '
b1000 (
#28300000000
b010 #
b010 '
#28400000000
b011 #
b1010 $
b011 '
b1010 (
#28500000000
b100 #
b1001 $
b100 '
b1001 (
#28600000000
b101 #
b1111 $
b101 '
b1111 (
#28700000000
b110 #
b0110 $
b110 '
b0110 (
#28800000000
b111 #
b111 '
#28900000000
b000 #
b1000 $
b000 '
b1000 (
#29000000000
b001 #
b001 '
b1000 (
#29100000000
b010 #
b010 '
#29200000000
b011 #
b1010 $
b011 '
b1010 (
#29300000000
b100 #
b1001 $
b100 '
b1001 (
#29400000000
b101 #
b1111 $
b101 '
b1111 (
#29500000000
b110 #
b0110 $
b110 '
b0110 (
#29600000000
b111 #
b111 '
#29700000000
b000 #
b1000 $
b000 '
b1000 (
#29800000000
b001 #
b001 '
b1000 (
#29900000000
b010 #
b010 '
#30000000000
b011 #
b1010 $
b011 '
b1010 (
#30100000000
b100 #
b1001 $
b100 '
b1001 (
#30200000000
b101 #
b1111 $
b101 '
b1111 (
#30300000000
b110 #
b0110 $
b110 '
b0110 (
#30400000000
b111 #
b111 '
#30500000000
b000 #
b1000 $
b000 '
b1000 (
#30600000000
b001 #
b001 '
b1000 (
#30700000000
b010 #
b010 '
#30800000000
b011 #
b1010 $
b011 '
b1010 (
#30900000000
b100 #
b1001 $
b100 '
b1001 (
#31000000000
b101 #
b1111 $
b101 '
b1111 (
#31100000000
b110 #
b0110 $
b110 '
b0110 (
#31200000000
b111 #
b111 '
#31300000000
b000 #
b1000 $
b000 '
b1000 (
#31400000000
b001 #
b001 '
b1000 (
#31500000000
b010 #
b010 '
#31600000000
b011 #
b1010 $
b011 '
b1010 (
#31700000000
b100 #
b1001 $
b100 '
b1001 (
#31800000000
b101 #
b1111 $
b101 '
b1111 (
#31900000000
b110 #
b0110 $
b110 '
b0110 (
#32000000000
b111 #
b111 '
#32100000000
b000 #
b1000 $
b000 '
b1000 (
#32200000000
b001 #
b001 '
b1000 (
#32300000000
b010 #
b010 '
#32400000000
b011 #
b1010 $
b011 '
b1010 (
#32500000000
b100 #
b1001 $
b100 '
b1001 (
#32600000000
b101 #
b1111 $
b101 '
b1111 (
#32700000000
b110 #
b0110 $
b110 '
b0110 (
#32800000000
b111 #
b111 '
#32900000000
b000 #
b1000 $
b000 '
b1000 (
#33000000000
b001 #
b001 '
b1000 (
#33100000000
b010 #
b010 '
#33200000000
b011 #
b1010 $
b011 '
b1010 (
#33300000000
b100 #
b1001 $
b100 '
b1001 (
#33400000000
b101 #
b1111 $
b101 '
b1111 (
#33500000000
b110 #
b0110 $
b110 '
b0110 (
#33600000000
b111 #
b111 '
#33700000000
b000 #
b1000 $
b000 '
b1000 (
#33800000000
b001 #
b001 '
b1000 (
#33900000000
b010 #
b010 '
#34000000000
b011 #
b1010 $
b011 '
b1010 (
#34100000000
b100 #
b1001 $
b100 '
b1001 (
#34200000000
b101 #
b1111 $
b101 '
b1111 (
#34300000000
b110 #
b0110 $
b110 '
b0110 (
#34400000000
b111 #
b111 '
#34500000000
b000 #
b1000 $
b000 '
b1000 (
#34600000000
b001 #
b001 '
b1000 (
#34700000000
b010 #
b010 '
#34800000000
b011 #
b1010 $
b011 '
b1010 (
#34900000000
b100 #
b1001 $
b100 '
b1001 (
#35000000000
b101 #
b1111 $
b101 '
b1111 (
#35100000000
b110 #
b0110 $
b110 '
b0110 (
#35200000000
b111 #
b111 '
#35300000000
b000 #
b1000 $
b000 '
b1000 (
#35400000000
b001 #
b001 '
b1000 (
#35500000000
b010 #
b010 '
#35600000000
b011 #
b1010 $
b011 '
b1010 (
#35700000000
b100 #
b1001 $
b100 '
b1001 (
#35800000000
b101 #
b1111 $
b101 '
b1111 (
#35900000000
b110 #
b0110 $
b110 '
b0110 (
#36000000000
b111 #
b111 '
#36100000000
b000 #
b1000 $
b000 '
b1000 (
#36200000000
b001 #
b001 '
b1000 (
#36300000000
b010 #
b010 '
#36400000000
b011 #
b1010 $
b011 '
b1010 (
#36500000000
b100 #
b1001 $
b100 '
b1001 (
#36600000000
b101 #
b1111 $
b101 '
b1111 (
#36700000000
b110 #
b0110 $
b110 '
b0110 (
#36800000000
b111 #
b111 '
#36900000000
b000 #
b1000 $
b000 '
b1000 (
#37000000000
b001 #
b001 '
b1000 (
#37100000000
b010 #
b010 '
#37200000000
b011 #
b1010 $
b011 '
b1010 (
#37300000000
b100 #
b1001 $
b100 '
b1001 (
#37400000000
b101 #
b1111 $
b101 '
b1111 (
#37500000000
b110 #
b0110 $
b110 '
b0110 (
#37600000000
b111 #
b111 '
#37700000000
b000 #
b1000 $
b000 '
b1000 (
#37800000000
b001 #
b001 '
b1000 (
#37900000000
b010 #
b010 '
#38000000000
b011 #
b1010 $
b011 '
b1010 (
#38100000000
b100 #
b1001 $
b100 '
b1001 (
#38200000000
b101 #
b1111 $
b101 '
b1111 (
#38300000000
b110 #
b0110 $
b110 '
b0110 (
#38400000000
b111 #
b111 '
#38500000000
b000 #
b1000 $
b000 '
b1000 (
#38600000000
b001 #
b001 '
b1000 (
#38700000000
b010 #
b010 '
#38800000000
b011 #
b1010 $
b011 '
b1010 (
#38900000000
b100 #
b1001 $
b100 '
b1001 (
#39000000000
b101 #
b1111 $
b101 '
b1111 (
#39100000000
b110 #
b0110 $
b110 '
b0110 (
#39200000000
b111 #
b111 '
#39300000000
b000 #
b1000 $
b000 '
b1000 (
#39400000000
b001 #
b001 '
b1000 (
#39500000000
b010 #
b010 '
#39600000000
b011 #
b1010 $
b011 '
b1010 (
#39700000000
b100 #
b1001 $
b100 '
b1001 (
#39800000000
b101 #
b1111 $
b101 '
b1111 (
#39900000000
b110 #
b0110 $
b110 '
b0110 (
#40000000000
b111 #
b111 '
#40100000000
b000 #
b1000 $
b000 '
b1000 (
#40200000000
b001 #
b001 '
b1000 (
#40300000000
b010 #
b010 '
#40400000000
b011 #
b1010 $
b011 '
b1010 (
#40500000000
b100 #
b1001 $
b100 '
b1001 (
#40600000000
b101 #
b1111 $
b101 '
b1111 (
#40700000000
b110 #
b0110 $
b110 '
b0110 (
#40800000000
b111 #
b111 '
#40900000000
b000 #
b1000 $
b000 '
b1000 (
#41000000000
b001 #
b001 '
b1000 (
#41100000000
b010 #
b010 '
#41200000000
b011 #
b1010 $
b011 '
b1010 (
#41300000000
b100 #
b1001 $
b100 '
b1001 (
#41400000000
b101 #
b1111 $
b101 '
b1111 (
#41500000000
b110 #
b0110 $
b110 '
b0110 (
#41600000000
b111 #
b111 '
#41700000000
b000 #
b1000 $
b000 '
b1000 (
#41800000000
b001 #
b001 '
b1000 (
#41900000000
b010 #
b010 '
#42000000000
b011 #
b1010 $
b011 '
b1010 (
#42100000000
b100 #
b1001 $
b100 '
b1001 (
#42200000000
b101 #
b1111 $
b101 '
b1111 (
#42300000000
b110 #
b0110 $
b110 '
b0110 (
#42400000000
b111 #
b111 '
#42500000000
b000 #
b1000 $
b000 '
b1000 (
#42600000000
b001 #
b001 '
b1000 (
#42700000000
b010 #
b010 '
#42800000000
b011 #
b1010 $
b011 '
b1010 (
#42900000000
b100 #
b1001 $
b100 '
b1001 (
#43000000000
b101 #
b1111 $
b101 '
b1111 (
#43100000000
b110 #
b0110 $
b110 '
b0110 (
#43200000000
b111 #
b111 '
#43300000000
b000 #
b1000 $
b000 '
b1000 (
#43400000000
b001 #
b001 '
b1000 (
#43500000000
b010 #
b010 '
#43600000000
b011 #
b1010 $
b011 '
b1010 (
#43700000000
b100 #
b1001 $
b100 '
b1001 (
#43800000000
b101 #
b1111 $
b101 '
b1111 (
#43900000000
b110 #
b0110 $
b110 '
b0110 (
#44000000000
b111 #
b111 '
#44100000000
b000 #
b1000 $
b000 '
b1000 (
#44200000000
b001 #
b001 '
b1000 (
#44300000000
b010 #
b010 '
#44400000000
b011 #
b1010 $
b011 '
b1010 (
#44500000000
b100 #
b1001 $
b100 '
b1001 (
#44600000000
b101 #
b1111 $
b101 '
b1111 (
#44700000000
b110 #
b0110 $
b110 '
b0110 (
#44800000000
b111 #
b111 '
#44900000000
b000 #
b1000 $
b000 '
b1000 (
#45000000000
b001 #
b001 '
b1000 (
#45100000000
b010 #
b010 '
#45200000000
b011 #
b1010 $
b011 '
b1010 (
#45300000000
b100 #
b1001 $
b100 '
b1001 (
#45400000000
b101 #
b1111 $
b101 '
b1111 (
#45500000000
b110 #
b0110 $
b110 '
b0110 (
#45600000000
b111 #
b111 '
#45700000000
b000 #
b1000 $
b000 '
b1000 (
#45800000000
b001 #
b001 '
b1000 (
#45900000000
b010 #
b010 '
#46000000000
b011 #
b1010 $
b011 '
b1010 (
#46100000000
b100 #
b1001 $
b100 '
b1001 (
#46200000000
b101 #
b1111 $
b101 '
b1111 (
#46300000000
b110 #
b0110 $
b110 '
b0110 (
#46400000000
b111 #
b111 '
#46500000000
b000 #
b1000 $
b000 '
b1000 (
#46600000000
b001 #
b001 '
b1000 (
#46700000000
b010 #
b010 '
#46800000000
b011 #
b1010 $
b011 '
b1010 (
#46900000000
b100 #
b1001 $
b100 '
b1001 (
#47000000000
b101 #
b1111 $
b101 '
b1111 (
#47100000000
b110 #
b0110 $
b110 '
b0110 (
#47200000000
b111 #
b111 '
#47300000000
b000 #
b1000 $
b000 '
b1000 (
#47400000000
b001 #
b001 '
b1000 (
#47500000000
b010 #
b010 '
#47600000000
b011 #
b1010 $
b011 '
b1010 (
#47700000000
b100 #
b1001 $
b100 '
b1001 (
#47800000000
b101 #
b1111 $
b101 '
b1111 (
#47900000000
b110 #
b0110 $
b110 '
b0110 (
#48000000000
b111 #
b111 '
#48100000000
b000 #
b1000 $
b000 '
b1000 (
#48200000000
b001 #
b001 '
b1000 (
#48300000000
b010 #
b010 '
#48400000000
b011 #
b1010 $
b011 '
b1010 (
#48500000000
b100 #
b1001 $
b100 '
b1001 (
#48600000000
b101 #
b1111 $
b101 '
b1111 (
#48700000000
b110 #
b0110 $
b110 '
b0110 (
#48800000000
b111 #
b111 '
#48900000000
b000 #
b1000 $
b000 '
b1000 (
#49000000000
b001 #
b001 '
b1000 (
#49100000000
b010 #
b010 '
#49200000000
b011 #
b1010 $
b011 '
b1010 (
#49300000000
b100 #
b1001 $
b100 '
b1001 (
#49400000000
b101 #
b1111 $
b101 '
b1111 (
#49500000000
b110 #
b0110 $
b110 '
b0110 (
#49600000000
b111 #
b111 '
#49700000000
b000 #
b1000 $
b000 '
b1000 (
#49800000000
b001 #
b001 '
b1000 (
#49900000000
b010 #
b010 '
#50000000000
b011 #
b1010 $
b011 '
b1010 (
#50100000000
b100 #
b1001 $
b100 '
b1001 (
#50200000000
b101 #
b1111 $
b101 '
b1111 (
#50300000000
b110 #
b0110 $
b110 '
b0110 (
#50400000000
b111 #
b111 '
#50500000000
b000 #
b1000 $
b000 '
b1000 (
#50600000000
b001 #
b001 '
b1000 (
#50700000000
b010 #
b010 '
#50800000000
b011 #
b1010 $
b011 '
b1010 (
#50900000000
b100 #
b1001 $
b100 '
b1001 (
#51000000000
b101 #
b1111 $
b101 '
b1111 (
#51100000000
b110 #
b0110 $
b110 '
b0110 (
#51200000000
b111 #
b111 '
#51300000000
b000 #
b1000 $
b000 '
b1000 (
#51400000000
b001 #
b001 '
b1000 (
#51500000000
b010 #
b010 '
#51600000000
b011 #
b1010 $
b011 '
b1010 (
#51700000000
b100 #
b1001 $
b100 '
b1001 (
#51800000000
b101 #
b1111 $
b101 '
b1111 (
#51900000000
b110 #
b0110 $
b110 '
b0110 (
#52000000000
b111 #
b111 '
#52100000000
b000 #
b1000 $
b000 '
b1000 (
#52200000000
b001 #
b001 '
b1000 (
#52300000000
b010 #
b010 '
#52400000000
b011 #
b1010 $
b011 '
b1010 (
#52500000000
b100 #
b1001 $
b100 '
b1001 (
#52600000000
b101 #
b1111 $
b101 '
b1111 (
#52700000000
b110 #
b0110 $
b110 '
b0110 (
#52800000000
b111 #
b111 '
#52900000000
b000 #
b1000 $
b000 '
b1000 (
#53000000000
b001 #
b001 '
b1000 (
#53100000000
b010 #
b010 '
#53200000000
b011 #
b1010 $
b011 '
b1010 (
#53300000000
b100 #
b1001 $
b100 '
b1001 (
#53400000000
b101 #
b1111 $
b101 '
b1111 (
#53500000000
b110 #
b0110 $
b110 '
b0110 (
#53600000000
b111 #
b111 '
#53700000000
b000 #
b1000 $
b000 '
b1000 (
#53800000000
b001 #
b001 '
b1000 (
#53900000000
b010 #
b010 '
#54000000000
b011 #
b1010 $
b011 '
b1010 (
#54100000000
b100 #
b1001 $
b100 '
b1001 (
#54200000000
b101 #
b1111 $
b101 '
b1111 (
#54300000000
b110 #
b0110 $
b110 '
b0110 (
#54400000000
b111 #
b111 '
#54500000000
b000 #
b1000 $
b000 '
b1000 (
#54600000000
b001 #
b001 '
b1000 (
#54700000000
b010 #
b010 '
#54800000000
b011 #
b1010 $
b011 '
b1010 (
#54900000000
b100 #
b1001 $
b100 '
b1001 (
#55000000000
b101 #
b1111 $
b101 '
b1111 (
#55100000000
b110 #
b0110 $
b110 '
b0110 (
#55200000000
b111 #
b111 '
#55300000000
b000 #
b1000 $
b000 '
b1000 (
#55400000000
b001 #
b001 '
b1000 (
#55500000000
b010 #
b010 '
#55600000000
b011 #
b1010 $
b011 '
b1010 (
#55700000000
b100 #
b1001 $
b100 '
b1001 (
#55800000000
b101 #
b1111 $
b101 '
b1111 (
